MANIFEST.in
README.rst
mello.py
requirements.txt
setup.py
mello.egg-info/PKG-INFO
mello.egg-info/SOURCES.txt
mello.egg-info/dependency_links.txt
mello.egg-info/entry_points.txt
mello.egg-info/requires.txt
mello.egg-info/top_level.txt
todo/__init__.py
todo/configuration.py
todo/connection.py
todo/display.py
todo/exceptions.py
todo/input.py
todo/misc.py