Metadata-Version: 1.2
Name: mello
Version: 0.7.16
Summary: A Fast Command-line Interface for Trello
Home-page: https://github.com/whitef0x0/gtd.py
Author: David Baldwynn
Author-email: david@countable.ca
License: BSD 3-clause
Download-URL: https://github.com/whitef0x0/gtd.py/tarball/0.7.16
Keywords: productivity,cli,trello,gtd,getting things done
Platform: UNKNOWN
Classifier: Development Status :: 4 - Beta
Classifier: Environment :: Console
Classifier: Intended Audience :: Developers
Classifier: Intended Audience :: System Administrators
Classifier: Intended Audience :: End Users/Desktop
Classifier: License :: OSI Approved :: BSD License
Classifier: Natural Language :: English
Classifier: Operating System :: MacOS :: MacOS X
Classifier: Operating System :: POSIX :: Linux
Classifier: Operating System :: POSIX :: BSD
Classifier: Programming Language :: Python :: 3 :: Only
Classifier: Topic :: Utilities
Requires-Python: >=3
